emuSync/__init__.py
emuSync/configurationController.py
emuSync/emuSyncCmd.py
emuSync/emuSyncHooks.py
emuSync/emuSyncUI.py
emuSync/engineController.py
emuSync/ui_emuSyncUI.py
emuSync/workerClass.py
emuSync/workspaceController.py
emuSync/res/EmuSync.ico
emusync-9.21.367.3.dist-info/METADATA
emusync-9.21.367.3.dist-info/WHEEL
emusync-9.21.367.3.dist-info/entry_points.txt
emusync-9.21.367.3.dist-info/top_level.txt
emusync-9.21.367.3.dist-info/RECORD
