Metadata-Version: 2.4
Name: emuSync
Version: 9.21.367.3
Summary: TASKING emuSync
Author: TASKING
Project-URL: Homepage, https://support.tasking.com
Project-URL: Support, https://support.tasking.com/T
Classifier: Programming Language :: Python :: 3
Classifier: License :: OSI Approved :: GNU Lesser General Public License v3 (LGPLv3)
Classifier: Operating System :: OS Independent
Requires-Python: >=3.8
Requires-Dist: PyYAML
Requires-Dist: isystem.connect
Requires-Dist: PySide6
